[{"ent_seq":["2067800"],"k_ele":[{"keb":["戛戛"]},{"keb":["戛々"]},{"keb":["戞戞"]},{"keb":["戞々"]}],"r_ele":[{"reb":["かつかつ"]},{"reb":["カツカツ"],"re_nokanji":[{}]}],"sense":[{"pos":["adv-to"],"misc":["uk","on-mim"],"gloss":[{"xml:lang":"eng","$t":"clicking"},{"xml:lang":"eng","$t":"clopping"},{"xml:lang":"eng","$t":"clacking"}]},{"gloss":[{"xml:lang":"spa","$t":"ruido de objetos duros tocándose"},{"xml:lang":"spa","$t":"golpeo mutuo"}]}]},{"ent_seq":["2067800"],"k_ele":[{"keb":["戛戛"]},{"keb":["戛々"]},{"keb":["戞戞"]},{"keb":["戞々"]}],"r_ele":[{"reb":["かつかつ"]},{"reb":["カツカツ"],"re_nokanji":[{}]}],"sense":[{"pos":["adv-to"],"misc":["uk","on-mim"],"gloss":[{"xml:lang":"eng","$t":"clicking"},{"xml:lang":"eng","$t":"clopping"},{"xml:lang":"eng","$t":"clacking"}]},{"gloss":[{"xml:lang":"spa","$t":"ruido de objetos duros tocándose"},{"xml:lang":"spa","$t":"golpeo mutuo"}]}]},{"ent_seq":["2067800"],"k_ele":[{"keb":["戛戛"]},{"keb":["戛々"]},{"keb":["戞戞"]},{"keb":["戞々"]}],"r_ele":[{"reb":["かつかつ"]},{"reb":["カツカツ"],"re_nokanji":[{}]}],"sense":[{"pos":["adv-to"],"misc":["uk","on-mim"],"gloss":[{"xml:lang":"eng","$t":"clicking"},{"xml:lang":"eng","$t":"clopping"},{"xml:lang":"eng","$t":"clacking"}]},{"gloss":[{"xml:lang":"spa","$t":"ruido de objetos duros tocándose"},{"xml:lang":"spa","$t":"golpeo mutuo"}]}]}]