[{"ent_seq":["1158380"],"k_ele":[{"keb":["移牒"]}],"r_ele":[{"reb":["いちょう"]}],"sense":[{"pos":["n","vs","vt"],"gloss":[{"xml:lang":"eng","$t":"notification to authorities"}]},{"gloss":[{"xml:lang":"ger","$t":"eine Behörde in Kenntnis setzen"},{"xml:lang":"ger","$t":"benachrichtigen"},{"xml:lang":"ger","$t":"Mitteilung an die zuständige Stelle"},{"xml:lang":"ger","$t":"Übermittlung an die zuständige Stelle"},{"xml:lang":"ger","$t":"amtliche Anfrage"}]},{"gloss":[{"xml:lang":"rus","$t":"сообщение надлежащим властям"},{"xml:lang":"rus","$t":"{～する} сообщать (передавать) по назначению"}]},{"gloss":[{"xml:lang":"spa","$t":"notificación a las autoridades"}]}]},{"ent_seq":["1497760"],"k_ele":[{"keb":["符丁"]},{"keb":["符帳"]},{"keb":["符牒"]}],"r_ele":[{"reb":["ふちょう"]}],"sense":[{"pos":["n"],"gloss":[{"xml:lang":"eng","$t":"symbol"},{"xml:lang":"eng","$t":"sign"},{"xml:lang":"eng","$t":"mark"}]},{"pos":["n"],"gloss":[{"xml:lang":"eng","$t":"(secret) price mark"}]},{"pos":["n"],"gloss":[{"xml:lang":"eng","$t":"secret language"},{"xml:lang":"eng","$t":"code"},{"xml:lang":"eng","$t":"cipher"},{"xml:lang":"eng","$t":"argot"},{"xml:lang":"eng","$t":"password"}]},{"gloss":[{"xml:lang":"ger","$t":"Zeichen"},{"xml:lang":"ger","$t":"Marke"},{"xml:lang":"ger","$t":"Chiffre"},{"xml:lang":"ger","$t":"Code"}]},{"gloss":[{"xml:lang":"ger","$t":"Losungswort"},{"xml:lang":"ger","$t":"Losung"},{"xml:lang":"ger","$t":"Parole"}]},{"gloss":[{"xml:lang":"ger","$t":"Jargon"},{"xml:lang":"ger","$t":"Rotwelsch"},{"xml:lang":"ger","$t":"Geheimsprache"}]},{"gloss":[{"xml:lang":"hun","$t":"célpont"},{"xml:lang":"hun","$t":"jel"},{"xml:lang":"hun","$t":"márka"},{"xml:lang":"hun","$t":"nyom"}]},{"gloss":[{"xml:lang":"rus","$t":"1) условный знак; тайнопись; шифр"},{"xml:lang":"rus","$t":"2) условная (зашифрованная) маркировка цен"},{"xml:lang":"rus","$t":"3) условный язык; арго; пароль"}]}]},{"ent_seq":["1652560"],"k_ele":[{"keb":["通牒"]}],"r_ele":[{"reb":["つうちょう"]}],"sense":[{"pos":["n","vs","vt"],"gloss":[{"xml:lang":"eng","$t":"notice"},{"xml:lang":"eng","$t":"notification"},{"xml:lang":"eng","$t":"memorandum"},{"xml:lang":"eng","$t":"circular"}]},{"gloss":[{"xml:lang":"dut","$t":"berichten"},{"xml:lang":"dut","$t":"mededelen"},{"xml:lang":"dut","$t":"meedelen"},{"xml:lang":"dut","$t":"informeren"},{"xml:lang":"dut","$t":"kennisgeven"},{"xml:lang":"dut","$t":"bericht"},{"xml:lang":"dut","$t":"mededeling"},{"xml:lang":"dut","$t":"aanmelding"},{"xml:lang":"dut","$t":"aanzegging"},{"xml:lang":"dut","$t":"kennisgeving"},{"xml:lang":"dut","$t":"notificatie"}]},{"gloss":[{"xml:lang":"dut","$t":"nota"}]},{"gloss":[{"xml:lang":"ger","$t":"Note"},{"xml:lang":"ger","$t":"schriftliche Mitteilung"},{"xml:lang":"ger","$t":"Umlaufschreiben"}]},{"gloss":[{"xml:lang":"ger","$t":"diplomatische Note"}]},{"gloss":[{"xml:lang":"hun","$t":"bejelentés"},{"xml:lang":"hun","$t":"figyelem"},{"xml:lang":"hun","$t":"tudomás"}]},{"gloss":[{"xml:lang":"rus","$t":"нота (дипломатическая); письменное уведомление"},{"xml:lang":"rus","$t":"{～する} уведомлять нотой; письменно уведомлять"}]}]},{"ent_seq":["1657700"],"k_ele":[{"keb":["最後通牒"]}],"r_ele":[{"reb":["さいごつうちょう"]}],"sense":[{"pos":["n"],"misc":["yoji"],"gloss":[{"xml:lang":"eng","$t":"ultimatum"}]},{"gloss":[{"xml:lang":"dut","$t":"ultimatum"},{"xml:lang":"dut","$t":"ultimatieve nota"}]},{"gloss":[{"xml:lang":"ger","$t":"Ultimatum"}]},{"gloss":[{"xml:lang":"rus","$t":"ультиматум"}]}]},{"ent_seq":["2686620"],"k_ele":[{"keb":["来牒"]}],"r_ele":[{"reb":["らいちょう"]}],"sense":[{"pos":["n"],"misc":["rare"],"gloss":[{"xml:lang":"eng","$t":"correspondence"},{"xml:lang":"eng","$t":"received letter or note"}]}]}]