[{"ent_seq":["1345620"],"k_ele":[{"keb":["鋤"]},{"keb":["犂"]}],"r_ele":[{"reb":["すき"]}],"sense":[{"pos":["n"],"s_inf":["esp. 鋤"],"gloss":[{"xml:lang":"eng","$t":"spade"}]},{"pos":["n"],"xref":["唐鋤"],"s_inf":["esp. 犂"],"gloss":[{"xml:lang":"eng","$t":"plough"},{"xml:lang":"eng","$t":"plow"}]},{"gloss":[{"xml:lang":"dut","$t":"spade"}]},{"gloss":[{"xml:lang":"dut","$t":"ploeg"}]},{"gloss":[{"xml:lang":"ger","$t":"Pflug"}]},{"gloss":[{"xml:lang":"ger","$t":"Spaten"}]},{"gloss":[{"xml:lang":"hun","$t":"ásónyomnyi mélység"},{"xml:lang":"hun","$t":"bálnadaraboló véső"},{"xml:lang":"hun","$t":"herélt állat"},{"xml:lang":"hun","$t":"kiherélt állat"},{"xml:lang":"hun","$t":"pikk"},{"xml:lang":"hun","$t":"eke"},{"xml:lang":"hun","$t":"szántás"}]},{"gloss":[{"xml:lang":"rus","$t":"плуг"},{"xml:lang":"rus","$t":"1) лопата, заступ"},{"xml:lang":"rus","$t":"2) плуг"}]}]},{"ent_seq":["1774820"],"k_ele":[{"keb":["唐鋤"]},{"keb":["犂"]}],"r_ele":[{"reb":["からすき"]}],"sense":[{"pos":["n"],"misc":["arch"],"gloss":[{"xml:lang":"eng","$t":"plow (esp. horse or ox-drawn)"},{"xml:lang":"eng","$t":"plough"}]},{"gloss":[{"xml:lang":"ger","$t":"chinesischer Pflug"}]},{"gloss":[{"xml:lang":"hun","$t":"eke"},{"xml:lang":"hun","$t":"szántás"}]},{"gloss":[{"xml:lang":"rus","$t":"китайский плуг"}]},{"gloss":[{"xml:lang":"swe","$t":"plog"}]}]},{"ent_seq":["2247820"],"k_ele":[{"keb":["唐鋤星"]},{"keb":["犂星"]},{"keb":["参宿"]}],"r_ele":[{"reb":["からすきぼし"]},{"reb":["しんしゅく"],"re_restr":["参宿"]}],"sense":[{"pos":["n"],"xref":["参・しん"],"misc":["rare"],"gloss":[{"xml:lang":"eng","$t":"Chinese \"Three Stars\" constellation (one of the 28 mansions)"}]}]}]