[{"ent_seq":["2177210"],"k_ele":[{"keb":["膂力"]}],"r_ele":[{"reb":["りょりょく"]}],"sense":[{"pos":["n"],"gloss":[{"xml:lang":"eng","$t":"physical strength"},{"xml:lang":"eng","$t":"the strength of one's muscles"}]},{"gloss":[{"xml:lang":"ger","$t":"Muskelkraft"},{"xml:lang":"ger","$t":"Körperkraft"}]},{"gloss":[{"xml:lang":"rus","$t":"(кн.) физическая сила"}]}]},{"ent_seq":["2179830"],"k_ele":[{"keb":["膂宍"]},{"keb":["背宍"]}],"r_ele":[{"reb":["そしし"]},{"reb":["そじし"]}],"sense":[{"pos":["n"],"misc":["arch"],"gloss":[{"xml:lang":"eng","$t":"meat, flesh, or muscles along the spine"}]}]}]