{"type":"character","codepoints":{"ucs":"672c","jis208":"1-43-60"},"radicals":{"classical":75,"nelson_c":2},"strokeCounts":[5],"variants":{"jis208":["1-52-81"]},"radNames":[],"dicRefs":{"nelson_c":["96"],"nelson_n":["2536"],"halpern_njecd":["3502"],"halpern_kkd":["4314"],"halpern_kkld":["2183"],"halpern_kkld_2ed":["2937"],"heisig":["211"],"heisig6":["224"],"gakken":["15"],"oneill_names":["212"],"oneill_kk":["20"],"moro":[{"vol":"6","page":"0026","value":"14421"}],"henshall":["70"],"sh_kk":["25"],"sh_kk2":["25"],"sakade":["45"],"jf_cards":["61"],"henshall3":["76"],"tutt_cards":["47"],"crowley":["6"],"kanji_in_context":["37"],"busy_people":["2.1"],"kodansha_compact":["1046"],"maniette":["215"]},"queryCodes":{"skip":[{"value":"4-5-3"}],"sh_desc":["0a5.25"],"four_corner":["5023.0"],"deroo":["1855"]},"readings":{"pinyin":["ben3"],"korean_r":["bon"],"korean_h":["본"],"vietnam":["Bổn","Bản"],"ja_on":["ホン"],"ja_kun":["もと"]},"meanings":{"en":["book","present","main","origin","true","real","counter for long cylindrical things"],"fr":["livre","présent","essentiel","origine","principal","réalité","vérité","compteur d'objets allongés"],"es":["libro","origen","base","contador de cosas alargadas"],"pt":["livro","presente","real","verdadeiro","principal","sufixo p/ contagem De coisas longas"]},"nanori":["まと","ごう"],"literal":"本","grade":1,"freq":10,"jlpt":4}