{"type":"character","codepoints":{"ucs":"5178","jis208":"1-37-21"},"radicals":{"classical":12},"strokeCounts":[8],"variants":{},"radNames":[],"dicRefs":{"nelson_c":["588"],"nelson_n":["375"],"halpern_njecd":["2627"],"halpern_kkd":["3253"],"halpern_kkld":["1680"],"halpern_kkld_2ed":["2283"],"heisig":["1827"],"heisig6":["1969"],"gakken":["956"],"oneill_names":["733"],"oneill_kk":["640"],"moro":[{"vol":"2","page":"0099","value":"1474"}],"henshall":["552"],"sh_kk":["367"],"sh_kk2":["368"],"sakade":["680"],"jf_cards":["1077"],"henshall3":["579"],"tutt_cards":["512"],"kanji_in_context":["630"],"kodansha_compact":["157"],"maniette":["1844"]},"queryCodes":{"skip":[{"value":"2-6-2"}],"sh_desc":["2o6.5"],"four_corner":["5580.1"],"deroo":["1961"]},"readings":{"pinyin":["dian3"],"korean_r":["jeon"],"korean_h":["전"],"vietnam":["Điển"],"ja_on":["テン","デン"],"ja_kun":["ふみ","のり"]},"meanings":{"en":["code","ceremony","law","rule"],"fr":["code","cérémonie","loi","règle"],"es":["escrito","ceremonia","ley","regla"],"pt":["código","cerimônia","lei","regra"]},"nanori":["すけ","つね","の"],"literal":"典","grade":4,"freq":1055,"jlpt":1}