{"type":"character","codepoints":{"ucs":"5fa0","jis208":"1-55-50"},"radicals":{"classical":60},"strokeCounts":[11],"variants":{"nelson_c":["202"]},"radNames":[],"dicRefs":{"nelson_c":["1616"],"nelson_n":["1748"],"halpern_kkd":["576"],"halpern_kkld_2ed":["434"],"oneill_names":["1297"],"moro":[{"vol":"4","page":"0887","value":"10155"}]},"queryCodes":{"skip":[{"value":"1-3-8"}],"sh_desc":["0a7.6"],"four_corner":["2429.8"]},"readings":{"pinyin":["lai2"],"korean_r":["rae"],"korean_h":["래"],"vietnam":["Lai","Lại"],"ja_on":["ライ"],"ja_kun":["きた.す","きた.る","く.る"]},"meanings":{"en":["induce","encourage to come"]},"nanori":[],"literal":"徠","grade":9}