{"type":"character","codepoints":{"ucs":"659b","jis208":"1-58-47"},"radicals":{"classical":68,"nelson_c":148},"strokeCounts":[11],"variants":{},"radNames":[],"dicRefs":{"nelson_c":["4302"],"nelson_n":["2375"],"moro":[{"vol":"5","page":"0613","value":"13508"}]},"queryCodes":{"skip":[{"value":"1-7-4"}],"sh_desc":["2n9.2"],"four_corner":["2420.0"]},"readings":{"pinyin":["hu2"],"korean_r":["gog"],"korean_h":["곡"],"vietnam":["Hộc"],"ja_on":["コク"],"ja_kun":["と"]},"meanings":{"en":["measure","ten to","unit of volume, about 180 liters"]},"nanori":[],"literal":"斛"}