{"type":"character","codepoints":{"ucs":"818f","jis208":"1-25-49"},"radicals":{"classical":130,"nelson_c":189},"strokeCounts":[14],"variants":{},"radNames":[],"dicRefs":{"nelson_c":["5250"],"nelson_n":["4860"],"halpern_njecd":["2141"],"halpern_kkd":["2658"],"halpern_kkld_2ed":["1839"],"heisig":["2923"],"heisig6":["2931"],"moro":[{"vol":"9","page":"0355","value":"29800"}]},"queryCodes":{"skip":[{"value":"2-2-12"}],"sh_desc":["2j12.1"],"four_corner":["0022.7"]},"readings":{"pinyin":["gao1","gao4"],"korean_r":["go"],"korean_h":["고"],"vietnam":["Cao","Cáo"],"ja_on":["コウ"],"ja_kun":["あぶら"]},"meanings":{"en":["fat","grease","lard","paste","ointment","plaster"]},"nanori":[],"literal":"膏","grade":9}