{"type":"character","codepoints":{"ucs":"9f13","jis208":"1-24-61"},"radicals":{"classical":207},"strokeCounts":[13],"variants":{"jis208":["1-83-73"]},"radNames":[],"dicRefs":{"nelson_c":["5415"],"nelson_n":["7076"],"halpern_njecd":["1786"],"halpern_kkd":["2241"],"halpern_kkld":["1168"],"halpern_kkld_2ed":["1589"],"heisig":["1444"],"heisig6":["1552"],"gakken":["1836"],"oneill_names":["1959"],"oneill_kk":["1064"],"moro":[{"vol":"12","page":"1054","value":"48330"}],"henshall":["1234"],"sh_kk":["1147"],"sh_kk2":["1200"],"jf_cards":["1926"],"tutt_cards":["1692"],"kanji_in_context":["1827"],"kodansha_compact":["1944"],"maniette":["1456"]},"queryCodes":{"skip":[{"value":"1-9-4"}],"sh_desc":["3p10.2"],"four_corner":["4414.7"],"deroo":["1467"]},"readings":{"pinyin":["gu3"],"korean_r":["go"],"korean_h":["고"],"vietnam":["Cổ"],"ja_on":["コ"],"ja_kun":["つづみ"]},"meanings":{"en":["drum","beat","rouse","muster"],"fr":["tambour","battement","encourager","appel (armée)"],"es":["golpeo","tambor","animar"],"pt":["tambor","batida","despertar","inspeção (militar)"]},"nanori":[],"literal":"鼓","grade":8,"freq":1795,"jlpt":1}